LICENSE
MANIFEST.in
README.md
README.rst
requirements.txt
setup.py
pyauto/__init__.py
pyauto.pki.egg-info/PKG-INFO
pyauto.pki.egg-info/SOURCES.txt
pyauto.pki.egg-info/dependency_links.txt
pyauto.pki.egg-info/requires.txt
pyauto.pki.egg-info/top_level.txt
pyauto/pki/__init__.py
pyauto/pki/commands.py
pyauto/pki/config.py
pyauto/pki/pkiutil.py
pyauto/pki/sshutil.py