Metadata-Version: 1.0
Name: pyauto.pki
Version: 0.1.0
Summary: Manages keys, cert requests, and certs in the style of EasyRSA.
Home-page: https://github.com/adamjaso/pyauto/tree/master/pki
Author: Adam Jaso
Author-email: UNKNOWN
License: GNU General Public License V2
Platform: UNKNOWN
